__init__.py
keycap.py
opk.py
opk-0.0.16.dist-info/LICENSE
opk-0.0.16.dist-info/METADATA
opk-0.0.16.dist-info/WHEEL
opk-0.0.16.dist-info/top_level.txt
opk-0.0.16.dist-info/RECORD
