Metadata-Version: 2.1
Name: opk
Version: 0.0.16
Summary: Open Programmatic Keycap
Author-email: "Matteo (Matt3o) Spinelli" <info@matt3o.com>
License: Apache License
Project-URL: Homepage, https://github.com/cubiq/OPK
Project-URL: Bug Tracker, https://github.com/cubiq/OPK/issues
Classifier: Programming Language :: Python :: 3
Classifier: License :: OSI Approved :: Apache Software License
Classifier: Operating System :: OS Independent
Requires-Python: >=3.7
License-File: LICENSE
Requires-Dist: cadquery (==2.2.0b1)
